{"Soups": ["Chicken Enchilada Soup", "Mulligatawny (V)"], "Plat Du Jour": ["Southwest Chicken & Rice Casserole", "Roasted Redskin Potatoes (V)", "Roasted White Corn & Poblano Peppers (V)"], "Vegan Special": ["Spicy Chickpea Samosas (V)", "Steamed White Rice (V)", "Roasted White Corn & Poblano Peppers (V)", "Mulligatawny (V)"], "Gluten Free": ["Cheese Quesadilla (OL)", "Picante Sauce (V)", "Roasted Redskin Potatoes (V)", "Roasted White Corn & Poblano Peppers (V)"], "Halal": ["Ground Beef Samosas (H)", "Roasted White Corn & Poblano Peppers (V)"], "Pizza Parlor": ["Chicken & Hoisin w-Scallions Pizza", "Pork Sausage Pizza", "Cheese Pizza (OL)"], "Saute Station": ["Pasta Rotini w-Sauce Rstd Red Pepper OL", "Rotini Pasta (V)", "Roasted Red Pepper Sauce (OL)", "Marinara Sauce (V)", "Crushed Red Pepper", "Parmesan Cheese (OL)"], "Stir Fry Station": ["Sesame Beef & Vegetable Stir-Fry", "Steamed White Rice (V)", "Kimchi (AL) (V)"], "Honor G Grill": ["Bourbon Batter Dipped Toast (OL)", "Maple Syrup (V)", "Char Grilled Hamburger (H)", "Char Grilled Cheeseburger", "Grilled Chicken Breast (H)", "Beyond Burger (V)", "Shoestring Fries"], "Roller Grill": ["Beef Hot Dog", "Coney Bun (V)", "Vegetarian Sweet Italian Sausage (V)", "Brats Bun (V)", "Chopped Yellow Onions (V)", "Sauerkraut (V)", "Sweet Green Pickle Relish (V)"], "Desserts": ["Lemon Poppy Seed Cupcake w- Raspberrry", "Banana Bars with Vanilla Frosting (OL)", "Crunchy Granola Cookies w- Pecans (V)"]}