{"date": "Mon, May 15 2023", "offerings": [{"Breakfast Pastry": ["Lemon Cream Cheese Strudel (OL)", "Chocolate Zucchini Muffin (AL) (V)"]}, {"Breakfast Pastry": ["Lemon Cream Cheese Strudel (OL)", "Chocolate Zucchini Muffin (AL) (V)"]}, {"Breakfast Pastry": ["Lemon Cream Cheese Strudel (OL)", "Chocolate Zucchini Muffin (AL) (V)"]}, {"Breakfast Pastry": ["Lemon Cream Cheese Strudel (OL)", "Chocolate Zucchini Muffin (AL) (V)"]}, {"Breakfast Pastry": ["Lemon Cream Cheese Strudel (OL)", "Chocolate Zucchini Muffin (AL) (V)"]}, {"Breakfast Pastry": ["Lemon Cream Cheese Strudel (OL)", "Chocolate Zucchini Muffin (AL) (V)"]}, {"Breakfast Pastry": ["Lemon Cream Cheese Strudel (OL)", "Chocolate Zucchini Muffin (AL) (V)"]}, {"Breakfast Pastry": ["Lemon Cream Cheese Strudel (OL)", "Chocolate Zucchini Muffin (AL) (V)"]}, {"Breakfast Pastry": ["Lemon Cream Cheese Strudel (OL)", "Chocolate Zucchini Muffin (AL) (V)"]}], "mealName": "Light Breakfast"}